LICENSE
README
setup.py
xpathwebdriver/ColorStreamHandler.py
xpathwebdriver/ImagesComparator.py
xpathwebdriver/__init__.py
xpathwebdriver/base.py
xpathwebdriver/browser.py
xpathwebdriver/default_settings.py
xpathwebdriver/levels.py
xpathwebdriver/logger.py
xpathwebdriver/simple_shell.py
xpathwebdriver/simple_xpath_browser.py
xpathwebdriver/solve_settings.py
xpathwebdriver/validators.py
xpathwebdriver/webdriver_manager.py
xpathwebdriver/xpath_browser.py
xpathwebdriver.egg-info/PKG-INFO
xpathwebdriver.egg-info/SOURCES.txt
xpathwebdriver.egg-info/dependency_links.txt
xpathwebdriver.egg-info/requires.txt
xpathwebdriver.egg-info/top_level.txt
xpathwebdriver/commands/xpathshell
xpathwebdriver_tests/__init__.py
xpathwebdriver_tests/test_ImagesComparator.py
xpathwebdriver_tests/test_XpathBrowser.py
xpathwebdriver_tests/wipe_alerts.py