Metadata-Version: 2.1
Name: xpathwebdriver
Version: 2.0.6
Summary: Selenium/webdriver wrapper for XPath and CSS selection
Home-page: https://github.com/joaduo/xpathwebdriver
Author: Joaquin Duo
Author-email: joaduo@gmail.com
License: MIT
Keywords: testing,automation,web,unittest,webdriver,selenium,xpath,css
Platform: UNKNOWN
License-File: LICENSE
